sensory_memory_adi/__init__.py
sensory_memory_adi/compat.py
sensory_memory_adi/core.py
sensory_memory_adi/py.typed
sensory_memory_adi/agi/__init__.py
sensory_memory_adi/agi/attention.py
sensory_memory_adi/buffers/__init__.py
sensory_memory_adi/buffers/echoic.py
sensory_memory_adi/buffers/haptic.py
sensory_memory_adi/buffers/iconic.py
sensory_memory_adi/concurrency/__init__.py
sensory_memory_adi/concurrency/ingestor.py
sensory_memory_adi/ext/__init__.py
sensory_memory_adi/feelings/__init__.py
sensory_memory_adi/feelings/haptics.py
sensory_memory_adi/feelings/sentiment.py
sensory_memory_adi/privacy/__init__.py
sensory_memory_adi/privacy/redaction.py
sensory_memory_adi/robotics/__init__.py
sensory_memory_adi/robotics/can/adapter.py
sensory_memory_adi/robotics/ros2/__init__.py
sensory_memory_adi/robotics/ros2/adapter.py
sensory_memory_adi/robotics/ros2/buffering.py
sensory_memory_adi/server/__init__.py
sensory_memory_adi/server/app.py
sensory_memory_adi/utils/ring.py
sensory_memory_adi/utils/time.py
sensory_memory_adi/zerocopy/__init__.py
sensory_memory_adi/zerocopy/frames.py
sensory_memory_adi-0.1.2.1.dist-info/licenses/LICENSE
sensory_memory_adi-0.1.2.1.dist-info/METADATA
sensory_memory_adi-0.1.2.1.dist-info/WHEEL
sensory_memory_adi-0.1.2.1.dist-info/top_level.txt
sensory_memory_adi-0.1.2.1.dist-info/RECORD
