Metadata-Version: 2.4
Name: sensory-memory-adi
Version: 0.1.2.1
Summary: Sensory Memory ADI: iconic/echoic/haptic short-buffers with attention routing, feeling-aware touch interpretation, and AGI-ready hooks for agentic systems.
Author: Adi's American Soft LLC
License: Apache-2.0
Keywords: sensory-memory,agentic-ai,agi-ready,buffers,multimodal,haptics,echoic,iconic,attention,privacy
Classifier: License :: OSI Approved :: Apache Software License
Classifier: Programming Language :: Python :: 3
Classifier: Programming Language :: Python :: 3 :: Only
Classifier: Topic :: Scientific/Engineering :: Artificial Intelligence
Classifier: Topic :: Software Development :: Libraries
Requires-Python: >=3.9
License-File: LICENSE
Requires-Dist: pydantic>=2.0; python_version >= "3.9"
Provides-Extra: numpy
Requires-Dist: numpy>=1.24; extra == "numpy"
Provides-Extra: speed
Requires-Dist: pybind11>=2.11; extra == "speed"
Provides-Extra: bench
Requires-Dist: numpy>=1.24; extra == "bench"
Provides-Extra: robotics
Requires-Dist: python-can>=4.4.0; extra == "robotics"
Provides-Extra: ros2
Provides-Extra: server
Requires-Dist: fastapi>=0.110; extra == "server"
Requires-Dist: uvicorn>=0.23; extra == "server"
Provides-Extra: llm
Requires-Dist: openai>=1.0.0; extra == "llm"
Provides-Extra: dev
Requires-Dist: pytest>=8.0; extra == "dev"
Requires-Dist: ruff>=0.6; extra == "dev"
Requires-Dist: mypy>=1.8; extra == "dev"
Requires-Dist: build>=1.2; extra == "dev"
Requires-Dist: twine>=5.0; extra == "dev"
Dynamic: license-file
